libshorttext-1.1.0.0.dist-info/metadata.json
libshorttext-1.1.0.0.dist-info/WHEEL
libshorttext-1.1.0.0.dist-info/top_level.txt
libshorttext-1.1.0.0.dist-info/DESCRIPTION.rst
libshorttext-1.1.0.0.dist-info/METADATA
libshorttext-1.1.0.0.dist-info/RECORD
libshorttext-1.1.0.0.dist-info/pbr.json
libshorttext/__init__.py
libshorttext/converter/converter_impl.py
libshorttext/converter/__init__.py
libshorttext/converter/stop-words/stoplist-nsp.regex.pickle
libshorttext/converter/stop-words/stoplist-nsp.regex
libshorttext/converter/stemmer/porter.so.1
libshorttext/converter/stemmer/porter.py
libshorttext/converter/stemmer/__init__.py
libshorttext/analyzer/selector.py
libshorttext/analyzer/__init__.py
libshorttext/analyzer/analyzer_impl.py
libshorttext/classifier/classifier_impl.py
libshorttext/classifier/grid.py
libshorttext/classifier/__init__.py
libshorttext/classifier/learner/learner_impl.py
libshorttext/classifier/learner/util.so.1
libshorttext/classifier/learner/__init__.py
libshorttext/classifier/learner/liblinear/liblinear.so.1
libshorttext/classifier/learner/liblinear/python/liblinearutil.py
libshorttext/classifier/learner/liblinear/python/liblinear.py
