Metadata-Version: 2.0
Name: libshorttext
Version: 1.1.0.0
Summary: LibShortText is an open source tool for short-text classification and analysis. It can handle the classification of, for example, titles, questions, sentences, and short messages
Home-page: http://www.csie.ntu.edu.tw/~cjlin/libshorttext/
Author: H.-F. Yu, C.-H. Ho, Y.-C. Juan, C.-J. Lin
Author-email: cjlin@csie.ntu.edu.tw
License: UNKNOWN
Keywords: liblinear,classifier,svm,short text,text
Platform: UNKNOWN
Classifier: Development Status :: 5 - Production/Stable
Classifier: Intended Audience :: Developers
Classifier: Intended Audience :: Education
Classifier: Intended Audience :: Science/Research
Classifier: License :: Freely Distributable
Classifier: Operating System :: POSIX
Classifier: Programming Language :: Python :: 2.6
Classifier: Programming Language :: Python :: 2.7
Classifier: Topic :: Scientific/Engineering :: Information Analysis
Classifier: Topic :: Software Development :: Libraries
Classifier: Topic :: Text Processing :: General
